{
    "categories": [
        {
            "id": "switches",
            "name": "Switches",
            "nameAr": "سويتشات",
            "icon": "Network",
            "subcategories": [
                {
                    "id": "poe-switch",
                    "name": "PoE Switch",
                    "nameAr": "سويتش PoE"
                },
                {
                    "id": "network-switch",
                    "name": "Network Switch",
                    "nameAr": "سويتش شبكة"
                }
            ]
        },
        {
            "id": "networking",
            "name": "Networking",
            "nameAr": "الشبكات",
            "icon": "Wifi",
            "subcategories": [
                {
                    "id": "router",
                    "name": "Router",
                    "nameAr": "راوتر"
                },
                {
                    "id": "antina",
                    "name": "Antina",
                    "nameAr": "أنتينا"
                }
            ]
        },
        {
            "id": "panels-enclosure-racks",
            "name": "Panels & Enclosure & Racks",
            "nameAr": "لوحات وخزائن ورفوف",
            "icon": "Server",
            "subcategories": [
                {
                    "id": "cable-management",
                    "name": "Cable management",
                    "nameAr": "إدارة الكابلات"
                },
                {
                    "id": "cabinet",
                    "name": "Cabinet",
                    "nameAr": "خزانة"
                }
            ]
        },
        {
            "id": "copper-system",
            "name": "Copper System",
            "nameAr": "نظام النحاس",
            "icon": "Cable",
            "subcategories": [
                {
                    "id": "copper-patch-cords",
                    "name": "Copper Patch Cords",
                    "nameAr": "كابلات توصيل نحاسية"
                },
                {
                    "id": "cables-copper",
                    "name": "Cables Copper",
                    "nameAr": "كابلات نحاسية"
                },
                {
                    "id": "connectors-jacks",
                    "name": "Connectors & Jacks",
                    "nameAr": "موصلات ومقابس"
                }
            ]
        },
        {
            "id": "printers-barcode-scanners",
            "name": "Printers & Barcode Scanners",
            "nameAr": "طابعات وماسحات باركود",
            "icon": "Printer",
            "subcategories": []
        },
        {
            "id": "parts",
            "name": "Parts",
            "nameAr": "قطع غيار",
            "icon": "Wrench",
            "subcategories": [
                {
                    "id": "poe-separator",
                    "name": "PoE Separator",
                    "nameAr": "فاصل PoE"
                },
                {
                    "id": "power-adapter",
                    "name": "Power Adapter",
                    "nameAr": "محول طاقة"
                }
            ]
        },
        {
            "id": "others",
            "name": "Others",
            "nameAr": "أخرى",
            "icon": "Package",
            "subcategories": []
        }
    ],
    "products": [
        {
            "id": "router-001",
            "name": "Enterprise Fiber Router",
            "nameAr": "راوتر فايبر للشركات",
            "category": "networking",
            "subcategory": "router",
            "image": "https://images.unsplash.com/photo-1606904825846-647eb07f5be2?w=400&h=300&fit=crop",
            "images": [
                "https://images.unsplash.com/photo-1606904825846-647eb07f5be2?w=800&h=600&fit=crop",
                "https://images.unsplash.com/photo-1544197150-b99a580bb7a8?w=800&h=600&fit=crop",
                "https://images.unsplash.com/photo-1558618666-fcd25c85cd64?w=800&h=600&fit=crop"
            ],
            "description": "High-performance enterprise-grade fiber optic router designed for businesses requiring stable and fast internet connectivity. Ideal for offices and commercial establishments.",
            "descriptionAr": "راوتر فايبر عالي الأداء مصمم للشركات التي تتطلب اتصال إنترنت مستقر وسريع. مثالي للمكاتب والمنشآت التجارية.",
            "specifications": [
                "Speed: Up to 1Gbps",
                "Ports: 4x Gigabit LAN, 1x WAN",
                "WiFi: Dual-band 802.11ac",
                "Security: WPA3, Firewall",
                "Management: Web UI, App Control"
            ],
            "videoUrl": "https://www.youtube.com/watch?v=example1",
            "catalogUrl": "/catalogs/router-001-catalog.pdf",
            "driversUrl": "/drivers/router-001-drivers.zip",
            "featured": true,
            "price": "Contact for Price"
        },
        {
            "id": "router-002",
            "name": "Dual-Band Wireless Router",
            "nameAr": "راوتر لاسلكي ثنائي الموجة",
            "category": "networking",
            "subcategory": "router",
            "image": "https://images.unsplash.com/photo-1558618666-fcd25c85cd64?w=400&h=300&fit=crop",
            "images": [
                "https://images.unsplash.com/photo-1558618666-fcd25c85cd64?w=800&h=600&fit=crop",
                "https://images.unsplash.com/photo-1606904825846-647eb07f5be2?w=800&h=600&fit=crop"
            ],
            "description": "Advanced dual-band wireless router with extended range coverage. Perfect for homes and small offices with multiple connected devices.",
            "descriptionAr": "راوتر لاسلكي متقدم ثنائي الموجة مع تغطية ممتدة. مثالي للمنازل والمكاتب الصغيرة مع أجهزة متعددة متصلة.",
            "specifications": [
                "Speed: 2.4GHz (450Mbps) + 5GHz (1300Mbps)",
                "Ports: 4x Gigabit LAN",
                "Antennas: 4 External High-Gain",
                "Coverage: Up to 200m²",
                "Features: QoS, Parental Control"
            ],
            "videoUrl": null,
            "catalogUrl": "/catalogs/router-002-catalog.pdf",
            "driversUrl": null,
            "featured": true,
            "price": "Contact for Price"
        },
        {
            "id": "router-003",
            "name": "4G LTE Mobile Router",
            "nameAr": "راوتر محمول 4G LTE",
            "category": "networking",
            "subcategory": "router",
            "image": "https://images.unsplash.com/photo-1544197150-b99a580bb7a8?w=400&h=300&fit=crop",
            "description": "Portable 4G LTE router with built-in battery. Take your internet connection anywhere with this compact and powerful device.",
            "descriptionAr": "راوتر 4G LTE محمول مع بطارية مدمجة. خذ اتصالك بالإنترنت في أي مكان مع هذا الجهاز المدمج والقوي.",
            "specifications": [
                "Network: 4G LTE Cat 4",
                "Speed: Up to 150Mbps Download",
                "Battery: 3000mAh (10hrs)",
                "Users: Up to 10 Devices",
                "SIM: Nano SIM Support"
            ],
            "videoUrl": null,
            "featured": false,
            "price": "Contact for Price"
        },
        {
            "id": "switch-001",
            "name": "24-Port Gigabit Managed Switch",
            "nameAr": "سويتش 24 منفذ جيجابت مُدار",
            "category": "switches",
            "subcategory": "network-switch",
            "image": "https://images.unsplash.com/photo-1558494949-ef010cbdcc31?w=400&h=300&fit=crop",
            "description": "Enterprise-class 24-port gigabit managed switch with advanced VLAN, QoS, and security features. Rack-mountable design for server rooms.",
            "descriptionAr": "سويتش مُدار بفئة المؤسسات 24 منفذ جيجابت مع ميزات VLAN وQoS والأمان المتقدمة. تصميم قابل للتركيب على الرف لغرف الخوادم.",
            "specifications": [
                "Ports: 24x 10/100/1000Mbps",
                "SFP: 2x SFP Uplink Ports",
                "Features: VLAN, QoS, IGMP Snooping",
                "Management: Web, CLI, SNMP",
                "Power: IEEE 802.3af/at PoE+ Optional"
            ],
            "videoUrl": "https://www.youtube.com/watch?v=example2",
            "featured": true,
            "price": "Contact for Price"
        },
        {
            "id": "switch-002",
            "name": "8-Port PoE+ Switch",
            "nameAr": "سويتش 8 منافذ PoE+",
            "category": "switches",
            "subcategory": "poe-switch",
            "image": "https://images.unsplash.com/photo-1551703599-6b3e8379aa8c?w=400&h=300&fit=crop",
            "description": "Power over Ethernet switch with 8 PoE+ ports. Ideal for IP cameras, access points, and VoIP phones without additional power cables.",
            "descriptionAr": "سويتش طاقة عبر الإيثرنت مع 8 منافذ PoE+. مثالي لكاميرات IP ونقاط الوصول وهواتف VoIP بدون كابلات طاقة إضافية.",
            "specifications": [
                "Ports: 8x 10/100/1000Mbps PoE+",
                "PoE Budget: 120W Total",
                "Per Port: Up to 30W",
                "Uplink: 2x Gigabit SFP",
                "Features: Auto MDI/MDIX"
            ],
            "videoUrl": null,
            "featured": false,
            "price": "Contact for Price"
        },
        {
            "id": "switch-003",
            "name": "5-Port Desktop Switch",
            "nameAr": "سويتش مكتبي 5 منافذ",
            "category": "switches",
            "subcategory": "network-switch",
            "image": "https://images.unsplash.com/photo-1563770660941-20978e870e26?w=400&h=300&fit=crop",
            "description": "Compact and affordable 5-port gigabit desktop switch. Plug-and-play operation, perfect for home networks and small offices.",
            "descriptionAr": "سويتش مكتبي جيجابت 5 منافذ صغير وبأسعار معقولة. تشغيل التوصيل والتشغيل، مثالي للشبكات المنزلية والمكاتب الصغيرة.",
            "specifications": [
                "Ports: 5x 10/100/1000Mbps",
                "Type: Unmanaged",
                "Power: External Adapter",
                "Features: Plug & Play",
                "Size: Compact Desktop"
            ],
            "videoUrl": null,
            "featured": false,
            "price": "Contact for Price"
        },
        {
            "id": "cable-001",
            "name": "Cat6 Network Cable - 305m Box",
            "nameAr": "كابل شبكة Cat6 - صندوق 305 متر",
            "category": "copper-system",
            "subcategory": "cables-copper",
            "image": "https://images.unsplash.com/photo-1563770557171-0a96e7f0b72d?w=400&h=300&fit=crop",
            "description": "Premium quality Cat6 UTP cable in bulk box. Ideal for professional network installations with high-speed data transmission.",
            "descriptionAr": "كابل Cat6 UTP عالي الجودة في صندوق بالجملة. مثالي لتركيبات الشبكات المهنية مع نقل بيانات عالي السرعة.",
            "specifications": [
                "Category: Cat6 UTP",
                "Length: 305 meters (1000ft)",
                "Speed: Up to 1Gbps",
                "Conductor: Pure Copper 23AWG",
                "Colors: Blue, Gray, White Available"
            ],
            "videoUrl": null,
            "featured": true,
            "price": "Contact for Price"
        },
        {
            "id": "cable-002",
            "name": "Fiber Optic Patch Cord SC-SC",
            "nameAr": "كابل فايبر أوبتك SC-SC",
            "category": "copper-system",
            "subcategory": "copper-patch-cords",
            "image": "https://images.unsplash.com/photo-1601412436009-d964bd02edbc?w=400&h=300&fit=crop",
            "description": "Single-mode fiber optic patch cord with SC connectors. Low insertion loss for long-distance high-speed data transmission.",
            "descriptionAr": "كابل فايبر أوبتك أحادي الوضع مع موصلات SC. فقد إدراج منخفض لنقل البيانات عالي السرعة لمسافات طويلة.",
            "specifications": [
                "Type: Single Mode 9/125μm",
                "Connectors: SC/UPC - SC/UPC",
                "Length: 1m, 2m, 3m, 5m Available",
                "Insertion Loss: <0.3dB",
                "Jacket: LSZH Yellow"
            ],
            "videoUrl": null,
            "featured": false,
            "price": "Contact for Price"
        },
        {
            "id": "cable-003",
            "name": "RJ45 Connectors Pack (100pcs)",
            "nameAr": "موصلات RJ45 علبة (100 قطعة)",
            "category": "copper-system",
            "subcategory": "connectors-jacks",
            "image": "https://images.unsplash.com/photo-1544197150-b99a580bb7a8?w=400&h=300&fit=crop",
            "description": "High-quality gold-plated RJ45 connectors for Cat5e and Cat6 cables. Easy to crimp with standard tools.",
            "descriptionAr": "موصلات RJ45 عالية الجودة مطلية بالذهب لكابلات Cat5e وCat6. سهلة التركيب بأدوات قياسية.",
            "specifications": [
                "Type: RJ45 8P8C",
                "Gold Plating: 50μ Micron",
                "Compatible: Cat5e, Cat6",
                "Quantity: 100 pieces/pack",
                "Design: Pass-Through Available"
            ],
            "videoUrl": null,
            "featured": false,
            "price": "Contact for Price"
        },
        {
            "id": "tool-001",
            "name": "Professional Crimping Tool Kit",
            "nameAr": "طقم أدوات التجعيد المهنية",
            "category": "others",
            "subcategory": null,
            "image": "https://images.unsplash.com/photo-1581092160562-40aa08e78837?w=400&h=300&fit=crop",
            "description": "Complete network cable crimping tool kit including crimper, cable tester, wire stripper, and RJ45 connectors.",
            "descriptionAr": "طقم أدوات تجعيد كابلات الشبكة الكامل يتضمن أداة التجعيد واختبار الكابلات ومزيل العزل وموصلات RJ45.",
            "specifications": [
                "Crimper: RJ45 & RJ11",
                "Tester: LED Cable Tester",
                "Stripper: Adjustable Blade",
                "Includes: 50x RJ45 Connectors",
                "Case: Carrying Bag Included"
            ],
            "videoUrl": "https://www.youtube.com/watch?v=example3",
            "featured": true,
            "price": "Contact for Price"
        },
        {
            "id": "tool-002",
            "name": "Network Cable Tester",
            "nameAr": "جهاز اختبار كابلات الشبكة",
            "category": "others",
            "subcategory": null,
            "image": "https://images.unsplash.com/photo-1581092160562-40aa08e78837?w=400&h=300&fit=crop",
            "description": "Digital network cable tester for RJ45 and RJ11 connections. Identifies open, short, and crossed wires instantly.",
            "descriptionAr": "جهاز اختبار كابلات الشبكة الرقمي لاتصالات RJ45 وRJ11. يحدد الأسلاك المفتوحة والقصيرة والمتقاطعة فوراً.",
            "specifications": [
                "Testing: RJ45, RJ11, BNC",
                "Display: LED Indicators",
                "Features: Auto-Scan Mode",
                "Power: 9V Battery",
                "Range: Remote Up to 300m"
            ],
            "videoUrl": null,
            "featured": false,
            "price": "Contact for Price"
        },
        {
            "id": "printer-001",
            "name": "Laser Multifunction Printer",
            "nameAr": "طابعة ليزر متعددة الوظائف",
            "category": "printers-barcode-scanners",
            "subcategory": null,
            "image": "https://images.unsplash.com/photo-1612815154858-60aa4c59eaa6?w=400&h=300&fit=crop",
            "description": "High-speed laser multifunction printer with print, scan, copy, and fax capabilities. Ideal for busy offices.",
            "descriptionAr": "طابعة ليزر متعددة الوظائف عالية السرعة مع إمكانيات الطباعة والمسح الضوئي والنسخ والفاكس. مثالية للمكاتب المشغولة.",
            "specifications": [
                "Print Speed: 35 ppm",
                "Resolution: 1200x1200 dpi",
                "Paper Capacity: 250 sheets",
                "Connectivity: USB, WiFi, Ethernet",
                "Functions: Print, Scan, Copy, Fax"
            ],
            "videoUrl": null,
            "featured": true,
            "price": "Contact for Price"
        },
        {
            "id": "printer-002",
            "name": "Thermal Label Printer",
            "nameAr": "طابعة ملصقات حرارية",
            "category": "printers-barcode-scanners",
            "subcategory": null,
            "image": "https://images.unsplash.com/photo-1579389083395-4507e98b5e67?w=400&h=300&fit=crop",
            "description": "Direct thermal label printer for shipping, barcode, and product labels. No ink or toner required.",
            "descriptionAr": "طابعة ملصقات حرارية مباشرة للشحن والباركود وملصقات المنتجات. لا يتطلب حبر أو تونر.",
            "specifications": [
                "Print Speed: 150mm/s",
                "Resolution: 203 dpi",
                "Label Width: 20-118mm",
                "Connectivity: USB, Bluetooth",
                "Media: Thermal Direct"
            ],
            "videoUrl": null,
            "featured": false,
            "price": "Contact for Price"
        },
        {
            "id": "printer-003",
            "name": "POS Receipt Printer",
            "nameAr": "طابعة إيصالات نقاط البيع",
            "category": "printers-barcode-scanners",
            "subcategory": null,
            "image": "https://images.unsplash.com/photo-1586953208270-767889fa9b4a?w=400&h=300&fit=crop",
            "description": "Fast and reliable thermal receipt printer for point of sale systems. Compatible with all major POS software.",
            "descriptionAr": "طابعة إيصالات حرارية سريعة وموثوقة لأنظمة نقاط البيع. متوافقة مع جميع برامج نقاط البيع الرئيسية.",
            "specifications": [
                "Print Speed: 250mm/s",
                "Paper Width: 80mm",
                "Auto Cutter: Full & Partial",
                "Connectivity: USB, Serial, LAN",
                "Compatibility: Windows, Linux"
            ],
            "videoUrl": null,
            "featured": false,
            "price": "Contact for Price"
        },
        {
            "id": "scanner-001",
            "name": "Wireless 2D Barcode Scanner",
            "nameAr": "ماسح باركود 2D لاسلكي",
            "category": "printers-barcode-scanners",
            "subcategory": null,
            "image": "https://images.unsplash.com/photo-1558618666-fcd25c85cd64?w=400&h=300&fit=crop",
            "description": "High-performance wireless 2D barcode scanner with long battery life. Reads QR codes and all 1D/2D barcodes.",
            "descriptionAr": "ماسح باركود 2D لاسلكي عالي الأداء مع عمر بطارية طويل. يقرأ رموز QR وجميع باركودات 1D/2D.",
            "specifications": [
                "Type: 2D CMOS Imager",
                "Wireless: 2.4GHz + Bluetooth",
                "Battery: 2400mAh Li-ion",
                "Range: Up to 100m",
                "Reads: 1D, 2D, QR, PDF417"
            ],
            "videoUrl": "https://www.youtube.com/watch?v=example4",
            "featured": true,
            "price": "Contact for Price"
        },
        {
            "id": "scanner-002",
            "name": "Desktop Barcode Scanner",
            "nameAr": "ماسح باركود مكتبي",
            "category": "printers-barcode-scanners",
            "subcategory": null,
            "image": "https://images.unsplash.com/photo-1558618666-fcd25c85cd64?w=400&h=300&fit=crop",
            "description": "Hands-free desktop barcode scanner with presentation mode. Perfect for retail checkout and inventory management.",
            "descriptionAr": "ماسح باركود مكتبي بدون استخدام اليدين مع وضع العرض. مثالي للدفع بالتجزئة وإدارة المخزون.",
            "specifications": [
                "Scan Mode: Hands-Free & Trigger",
                "Light Source: 650nm Visible Laser",
                "Interface: USB HID Keyboard",
                "Read Rate: 300 scans/sec",
                "Mounting: Desktop Stand Included"
            ],
            "videoUrl": null,
            "featured": false,
            "price": "Contact for Price"
        },
        {
            "id": "scanner-003",
            "name": "USB Handheld Barcode Scanner",
            "nameAr": "ماسح باركود يدوي USB",
            "category": "printers-barcode-scanners",
            "subcategory": null,
            "image": "https://images.unsplash.com/photo-1558618666-fcd25c85cd64?w=400&h=300&fit=crop",
            "description": "Affordable USB wired barcode scanner for 1D barcodes. Plug and play with no driver installation required.",
            "descriptionAr": "ماسح باركود USB سلكي بسعر معقول لباركودات 1D. التوصيل والتشغيل بدون الحاجة لتثبيت برنامج تشغيل.",
            "specifications": [
                "Type: 1D Laser Scanner",
                "Interface: USB Plug & Play",
                "Read Distance: 5-30cm",
                "Indicators: LED + Beeper",
                "Cable: 1.5m USB Cable"
            ],
            "videoUrl": null,
            "featured": false,
            "price": "Contact for Price"
        },
        {
            "id": "other-001",
            "name": "Rack-Mount UPS 3000VA",
            "nameAr": "UPS للخادم 3000VA",
            "category": "others",
            "subcategory": null,
            "image": "https://images.unsplash.com/photo-1558618666-fcd25c85cd64?w=400&h=300&fit=crop",
            "description": "Online double-conversion UPS for server rooms and data centers. Provides clean power and extended runtime.",
            "descriptionAr": "UPS تحويل مزدوج عبر الإنترنت لغرف الخوادم ومراكز البيانات. يوفر طاقة نظيفة ووقت تشغيل ممتد.",
            "specifications": [
                "Capacity: 3000VA / 2700W",
                "Type: Online Double Conversion",
                "Runtime: 10 mins at full load",
                "Form Factor: 2U Rack Mount",
                "Battery: Hot-Swappable"
            ],
            "videoUrl": null,
            "featured": false,
            "price": "Contact for Price"
        },
        {
            "id": "other-002",
            "name": "Network Server Rack 42U",
            "nameAr": "خزانة خادم شبكة 42U",
            "category": "panels-enclosure-racks",
            "subcategory": "cabinet",
            "image": "https://images.unsplash.com/photo-1558494949-ef010cbdcc31?w=400&h=300&fit=crop",
            "description": "Professional 42U floor-standing server rack with cable management. Lockable doors and adjustable mounting rails.",
            "descriptionAr": "خزانة خادم أرضية 42U احترافية مع إدارة الكابلات. أبواب قابلة للقفل وقضبان تركيب قابلة للتعديل.",
            "specifications": [
                "Height: 42U (2000mm)",
                "Depth: 1000mm",
                "Load Capacity: 800kg",
                "Doors: Front Glass, Rear Metal",
                "Accessories: Fans, PDU Optional"
            ],
            "videoUrl": null,
            "featured": false,
            "price": "Contact for Price"
        },
        {
            "id": "other-003",
            "name": "Media Converter Fiber to Ethernet",
            "nameAr": "محول فايبر إلى إيثرنت",
            "category": "others",
            "subcategory": null,
            "image": "https://images.unsplash.com/photo-1563770660941-20978e870e26?w=400&h=300&fit=crop",
            "description": "Fiber optic to Gigabit Ethernet media converter. Extend network distances up to 20km using single-mode fiber.",
            "descriptionAr": "محول فايبر أوبتك إلى إيثرنت جيجابت. تمديد مسافات الشبكة حتى 20 كم باستخدام فايبر أحادي الوضع.",
            "specifications": [
                "Fiber: Single Mode 1310nm",
                "Ethernet: 10/100/1000Mbps",
                "Distance: Up to 20km",
                "Connector: SC Fiber, RJ45",
                "Power: 5V DC Adapter"
            ],
            "videoUrl": null,
            "featured": true,
            "price": "Contact for Price"
        }
    ]
}